{
    "0": {
        "Name": "Eleonora",
        "Surname": "Miani",
        "House": "B",
        "Day": [
            [
                "mon",
                "Morning"
            ],
            [
                "mon",
                "Afternoon"
            ],
            [
                "tue",
                "Afternoon"
            ]
        ]
    },
    "1": {
        "Name": "Elly",
        "Surname": "Miani",
        "House": "C",
        "Day": [
            [
                "mon",
                "Morning"
            ],
            [
                "tue",
                "Afternoon"
            ],
            [
                "thu",
                "Morning"
            ],
            [
                "thu",
                "Afternoon"
            ],
            [
                "fri",
                "Afternoon"
            ]
        ]
    },
    "2": {
        "Name": "Enrico",
        "Surname": "Petrucci",
        "House": "A",
        "Day": [
            [
                "mon",
                "Afternoon"
            ],
            [
                "tue",
                "Afternoon"
            ]
        ]
    },
    "3": {
        "Name": "Bobby",
        "Surname": "Morse",
        "House": "A",
        "Day": [
            [
                "mon",
                "Morning"
            ]
        ]
    },
    "4": {
        "Name": "Fitz",
        "Surname": "Simmons",
        "House": "D",
        "Day": [
            [
                "mon",
                "Morning"
            ],
            [
                "tue",
                "Morning"
            ],
            [
                "wed",
                "Afternoon"
            ],
            [
                "fri",
                "Afternoon"
            ]
        ]
    },
    "5": {
        "Name": "Anthony",
        "Surname": "DiNozzo",
        "House": "C",
        "Day": [
            [
                "mon",
                "Morning"
            ],
            [
                "tue",
                "Morning"
            ]
        ]
    },
    "6": {
        "Name": "Elly",
        "Surname": "Miani",
        "House": "C",
        "Day": [
            [
                "mon",
                "Morning"
            ],
            [
                "tue",
                "Afternoon"
            ],
            [
                "wed",
                "Afternoon"
            ]
        ]
    },
    "7": {
        "Name": "Leroy",
        "Surname": "Gibbs",
        "House": "C",
        "Day": [
            [
                "mon",
                "Morning"
            ],
            [
                "tue",
                "Morning"
            ],
            [
                "thu",
                "Afternoon"
            ],
            [
                "fri",
                "Afternoon"
            ]
        ]
    },
    "8": {
        "Name": "Bob",
        "Surname": "Tuttofare",
        "House": "C",
        "Day": [
            [
                "wed",
                "Morning"
            ],
            [
                "thu",
                "Afternoon"
            ],
            [
                "fri",
                "Afternoon"
            ]
        ]
    },
    "9": {
        "Name": "ce la faremo",
        "Surname": "forse no",
        "House": "B",
        "Day": [
            [
                "tue",
                "Morning"
            ],
            [
                "wed",
                "Morning"
            ],
            [
                "wed",
                "Afternoon"
            ],
            [
                "thu",
                "Afternoon"
            ]
        ]
    },
    "10": {
        "Name": "Can't",
        "Surname": "Anymore",
        "House": "C",
        "Day": [
            [
                "wed",
                "Morning"
            ],
            [
                "wed",
                "Afternoon"
            ],
            [
                "thu",
                "Afternoon"
            ],
            [
                "fri",
                "Afternoon"
            ]
        ]
    }
}